image_format_converter/__init__.py
image_format_converter/converter.py
image_format_converter-0.1.1.dist-info/LICENSE
image_format_converter-0.1.1.dist-info/METADATA
image_format_converter-0.1.1.dist-info/WHEEL
image_format_converter-0.1.1.dist-info/entry_points.txt
image_format_converter-0.1.1.dist-info/RECORD
