Metadata-Version: 2.1
Name: image_format_converter
Version: 0.1.1
Summary: A lightweight Python package that converts images in a directory from one format to another while preserving their dimensions.
Home-page: https://github.com/0xCaponte/image_format_converter
Author: Carlos Aponte
Author-email: carlos@caponte.io
Requires-Python: >=3.6,<4.0
Classifier: License :: OSI Approved :: MIT License
Classifier: Operating System :: OS Independent
Classifier: Programming Language :: Python :: 3
Classifier: Programming Language :: Python :: 3.6
Classifier: Programming Language :: Python :: 3.7
Classifier: Programming Language :: Python :: 3.8
Classifier: Programming Language :: Python :: 3.9
Classifier: Programming Language :: Python :: 3.10
Classifier: Programming Language :: Python :: 3.11
Requires-Dist: Pillow
